PoorHTTP-1.0.0.data/data/share/doc/poorhttp/COPYING
PoorHTTP-1.0.0.data/data/share/doc/poorhttp/ChangeLog
PoorHTTP-1.0.0.data/data/share/doc/poorhttp/README.rst
PoorHTTP-1.0.0.data/data/share/doc/poorhttp/about.rst
PoorHTTP-1.0.0.data/data/share/poorhttp/example/simple.py
etc/poorhttp.ini
etc/init.d/poorhttp
poorhttp/__init__.py
poorhttp/__main__.py
poorhttp/classes.py
poorhttp/config.py
poorhttp/daemon.py
poorhttp/main.py
PoorHTTP-1.0.0.dist-info/COPYING
PoorHTTP-1.0.0.dist-info/COPYING~
PoorHTTP-1.0.0.dist-info/METADATA
PoorHTTP-1.0.0.dist-info/WHEEL
PoorHTTP-1.0.0.dist-info/entry_points.txt
PoorHTTP-1.0.0.dist-info/top_level.txt
PoorHTTP-1.0.0.dist-info/RECORD
