Metadata-Version: 2.1
Name: PoorHTTP
Version: 1.0.0
Summary: Http/WSGI server for Python
Home-page: http://poorhttp.zeropage.cz/poorhttp
Author: Ondřej Tůma
Author-email: mcbig@zeropage.cz
Maintainer: Ondrej Tuma
Maintainer-email: mcbig@zeropage.cz
License: BSD
Platform: UNKNOWN
Classifier: Development Status :: 5 - Production/Stable
Classifier: Environment :: No Input/Output (Daemon)
Classifier: Intended Audience :: Customer Service
Classifier: Intended Audience :: Developers
Classifier: License :: OSI Approved :: BSD License
Classifier: Natural Language :: English
Classifier: Natural Language :: Czech
Classifier: Programming Language :: Python :: 3 :: Only
Classifier: Topic :: Internet :: WWW/HTTP :: WSGI :: Server
Requires-Python: >=3
Requires-Dist: lockfile
Requires-Dist: python-daemon
